dask_ec2/__init__.py
dask_ec2/_version.py
dask_ec2/cluster.py
dask_ec2/compatibility.py
dask_ec2/config.py
dask_ec2/ec2.py
dask_ec2/exceptions.py
dask_ec2/instance.py
dask_ec2/libpepper.py
dask_ec2/salt.py
dask_ec2/ssh.py
dask_ec2/utils.py
dask_ec2/cli/__init__.py
dask_ec2/cli/dask_shell.py
dask_ec2/cli/daskd.py
dask_ec2/cli/main.py
dask_ec2/cli/notebook.py
dask_ec2/cli/utils.py
dask_ec2/formulas/pillar/top.sls
dask_ec2/formulas/salt/top.sls
dask_ec2/formulas/salt/conda/debug.sls
dask_ec2/formulas/salt/conda/init.sls
dask_ec2/formulas/salt/conda/settings.sls
dask_ec2/formulas/salt/conda/templates/conda.sh
dask_ec2/formulas/salt/dask/distributed/debug.sls
dask_ec2/formulas/salt/dask/distributed/init.sls
dask_ec2/formulas/salt/dask/distributed/settings.sls
dask_ec2/formulas/salt/dask/distributed/scheduler/init.sls
dask_ec2/formulas/salt/dask/distributed/templates/dask-scheduler.conf
dask_ec2/formulas/salt/dask/distributed/templates/dask-worker.conf
dask_ec2/formulas/salt/dask/distributed/worker/init.sls
dask_ec2/formulas/salt/java/debug.sls
dask_ec2/formulas/salt/java/init.sls
dask_ec2/formulas/salt/java/settings.sls
dask_ec2/formulas/salt/java/openjdk/env.sls
dask_ec2/formulas/salt/java/openjdk/init.sls
dask_ec2/formulas/salt/java/openjdk/settings.sls
dask_ec2/formulas/salt/java/openjdk/templates/java.sh
dask_ec2/formulas/salt/jupyter/init.sls
dask_ec2/formulas/salt/jupyter/settings.sls
dask_ec2/formulas/salt/jupyter/notebook/init.sls
dask_ec2/formulas/salt/jupyter/notebook/settings.sls
dask_ec2/formulas/salt/jupyter/templates/jupyter-notebook.conf
dask_ec2/formulas/salt/jupyter/templates/jupyter_notebook_config_py
dask_ec2/formulas/salt/supervisor/init.sls
dask_ec2/formulas/salt/supervisor/settings.sls
dask_ec2/formulas/salt/system/base.sls
dask_ec2/formulas/salt/system/macros.sls
dask_ec2/formulas/salt/system/templates/limits.conf
dask_ec2/templates/auto_accept.conf
dask_ec2/templates/external_auth.conf
dask_ec2-0.4.0.dist-info/DESCRIPTION.rst
dask_ec2-0.4.0.dist-info/METADATA
dask_ec2-0.4.0.dist-info/RECORD
dask_ec2-0.4.0.dist-info/WHEEL
dask_ec2-0.4.0.dist-info/entry_points.txt
dask_ec2-0.4.0.dist-info/metadata.json
dask_ec2-0.4.0.dist-info/top_level.txt
